ca_certificates/__init__.py
python3_autopep8-0.0.0.dist-info/METADATA
python3_autopep8-0.0.0.dist-info/WHEEL
python3_autopep8-0.0.0.dist-info/top_level.txt
python3_autopep8-0.0.0.dist-info/RECORD
